[
  {
    "color": "",
    "year": 2022,
    "month": 3,
    "day": 11,
    "begClass": 7,
    "endClass": 8,
    "courseName": "内科学",
    "teacher": "谢东阳",
    "courseContent": "心力衰竭",
    "classroom": "118大班"
  },
  {
    "color": "",
    "year": 2022,
    "month": 3,
    "day": 14,
    "begClass": 1,
    "endClass": 2,
    "courseName": "内科学",
    "teacher": "谢东阳",
    "courseContent": "心力衰竭",
    "classroom": "206大班"
  },
  {
    "color": "",
    "year": 2022,
    "month": 3,
    "day": 14,
    "begClass": 7,
    "endClass": 8,
    "courseName": "核医学",
    "teacher": "黄谋清(外聘)",
    "courseContent": "pet/ct",
    "classroom": "202大班"
  },
  {
    "color": "",
    "year": 2022,
    "month": 3,
    "day": 15,
    "begClass": 1,
    "endClass": 2,
    "courseName": "中医学",
    "teacher": "刘海华",
    "courseContent": "病因病机",
    "classroom": "417大班"
  },
  {
    "color": "",
    "year": 2022,
    "month": 3,
    "day": 15,
    "begClass": 3,
    "endClass": 4,
    "courseName": "医学影像学",
    "teacher": "刘荣玮",
    "courseContent": "超声诊断实践",
    "classroom": "206大班"
  },
  {
    "color": "",
    "year": 2022,
    "month": 3,
    "day": 15,
    "begClass": 5,
    "endClass": 6,
    "courseName": "医学伦理学",
    "teacher": "肖杰峰",
    "courseContent": "医学伦理学的基本观点和理论",
    "classroom": "322大班"
  },
  {
    "color": "",
    "year": 2022,
    "month": 3,
    "day": 15,
    "begClass": 7,
    "endClass": 8,
    "courseName": "医学影像学",
    "teacher": "任苓",
    "courseContent": "妇科、产科超声诊断",
    "classroom": "222大班"
  },
  {
    "color": "",
    "year": 2022,
    "month": 3,
    "day": 17,
    "begClass": 1,
    "endClass": 2,
    "courseName": "内科学",
    "teacher": "谢东明",
    "courseContent": "心律失常",
    "classroom": "206大班"
  },
  {
    "color": "",
    "year": 2022,
    "month": 3,
    "day": 17,
    "begClass": 3,
    "endClass": 4,
    "courseName": "全科医学概论",
    "teacher": "张琼",
    "courseContent": "以人为中心的健康照顾（2）",
    "classroom": "206大班"
  },
  {
    "color": "",
    "year": 2022,
    "month": 3,
    "day": 17,
    "begClass": 5,
    "endClass": 8,
    "courseName": "预防医学",
    "teacher": "董明华;李思思;罗江洪;邱伟;刘明斌;吴清锋;郭雪梅;何小娜",
    "courseContent": "实验一  吸烟与肺癌",
    "classroom": "spss1-8实验室(黄)"
  },
  {
    "color": "",
    "year": 2022,
    "month": 3,
    "day": 20,
    "begClass": 3,
    "endClass": 4,
    "courseName": "预防医学",
    "teacher": "李思思",
    "courseContent": "第六章 筛检与诊断试验",
    "classroom": "105大班"
  },
  {
    "color": "",
    "year": 2022,
    "month": 3,
    "day": 21,
    "begClass": 1,
    "endClass": 2,
    "courseName": "核医学",
    "teacher": "黄铀新",
    "courseContent": "骨骼系统",
    "classroom": "623大班"
  },
  {
    "color": "",
    "year": 2022,
    "month": 3,
    "day": 21,
    "begClass": 7,
    "endClass": 8,
    "courseName": "中医学",
    "teacher": "孙小勇",
    "courseContent": "四诊",
    "classroom": "417大班"
  },
  {
    "color": "",
    "year": 2022,
    "month": 3,
    "day": 22,
    "begClass": 1,
    "endClass": 2,
    "courseName": "全科医学概论",
    "teacher": "朱韵雅",
    "courseContent": "以家庭为单位的健康照顾（1）",
    "classroom": "222大班"
  },
  {
    "color": "",
    "year": 2022,
    "month": 3,
    "day": 22,
    "begClass": 3,
    "endClass": 4,
    "courseName": "预防医学",
    "teacher": "吴清锋",
    "courseContent": "第八章 临床预防服务概论",
    "classroom": "206大班"
  },
  {
    "color": "",
    "year": 2022,
    "month": 3,
    "day": 22,
    "begClass": 5,
    "endClass": 6,
    "courseName": "内科学",
    "teacher": "谢东明",
    "courseContent": "心律失常",
    "classroom": "219大班"
  },
  {
    "color": "",
    "year": 2022,
    "month": 3,
    "day": 23,
    "begClass": 3,
    "endClass": 4,
    "courseName": "医学伦理学",
    "teacher": "肖杰峰",
    "courseContent": "医学伦理的规范体系",
    "classroom": "302大班"
  },
  {
    "color": "",
    "year": 2022,
    "month": 3,
    "day": 23,
    "begClass": 5,
    "endClass": 8,
    "courseName": "内科学",
    "teacher": "待定51",
    "courseContent": "呼吸系统疾病",
    "classroom": "见习场所4（章）"
  },
  {
    "color": "",
    "year": 2022,
    "month": 3,
    "day": 24,
    "begClass": 1,
    "endClass": 2,
    "courseName": "内科学",
    "teacher": "谢东明",
    "courseContent": "心律失常",
    "classroom": "317大班"
  },
  {
    "color": "",
    "year": 2022,
    "month": 3,
    "day": 24,
    "begClass": 5,
    "endClass": 6,
    "courseName": "医学影像学",
    "teacher": "郭少华",
    "courseContent": "中枢神经系统",
    "classroom": "206大班"
  },
  {
    "color": "",
    "year": 2022,
    "month": 3,
    "day": 24,
    "begClass": 7,
    "endClass": 8,
    "courseName": "内科学",
    "teacher": "凌嘉源",
    "courseContent": "高血压病",
    "classroom": "217大班"
  },
  {
    "color": "",
    "year": 2022,
    "month": 3,
    "day": 25,
    "begClass": 3,
    "endClass": 4,
    "courseName": "预防医学",
    "teacher": "何小娜",
    "courseContent": "第九章 健康行为干预",
    "classroom": "206大班"
  },
  {
    "color": "",
    "year": 2022,
    "month": 3,
    "day": 25,
    "begClass": 5,
    "endClass": 6,
    "courseName": "内科学",
    "teacher": "凌嘉源",
    "courseContent": "高血压病",
    "classroom": "217大班"
  },
  {
    "color": "",
    "year": 2022,
    "month": 3,
    "day": 25,
    "begClass": 7,
    "endClass": 8,
    "courseName": "预防医学",
    "teacher": "熊亮(公卫)",
    "courseContent": "chapter 7 public health surveillance and outbreak investigation",
    "classroom": "204大班"
  },
  {
    "color": "",
    "year": 2022,
    "month": 3,
    "day": 26,
    "begClass": 7,
    "endClass": 8,
    "courseName": "医学影像学",
    "teacher": "郭少华",
    "courseContent": "中枢神经系统",
    "classroom": "217大班"
  },
  {
    "color": "",
    "year": 2022,
    "month": 3,
    "day": 28,
    "begClass": 3,
    "endClass": 4,
    "courseName": "预防医学",
    "teacher": "林芬",
    "courseContent": "第十一章 合理营养指导（1）",
    "classroom": "206大班"
  },
  {
    "color": "",
    "year": 2022,
    "month": 3,
    "day": 28,
    "begClass": 5,
    "endClass": 6,
    "courseName": "预防医学",
    "teacher": "林芬",
    "courseContent": "第十一章 合理营养指导（2）",
    "classroom": "206大班"
  },
  {
    "color": "",
    "year": 2022,
    "month": 3,
    "day": 28,
    "begClass": 7,
    "endClass": 8,
    "courseName": "内科学",
    "teacher": "廖永玲",
    "courseContent": "冠心病",
    "classroom": "417大班"
  },
  {
    "color": "",
    "year": 2022,
    "month": 3,
    "day": 29,
    "begClass": 5,
    "endClass": 6,
    "courseName": "医学影像学",
    "teacher": "郭少华",
    "courseContent": "中枢神经系统",
    "classroom": "217大班"
  },
  {
    "color": "",
    "year": 2022,
    "month": 3,
    "day": 29,
    "begClass": 7,
    "endClass": 8,
    "courseName": "内科学",
    "teacher": "廖永玲",
    "courseContent": "冠心病",
    "classroom": "417大班"
  },
  {
    "color": "",
    "year": 2022,
    "month": 3,
    "day": 30,
    "begClass": 1,
    "endClass": 2,
    "courseName": "全科医学概论",
    "teacher": "朱韵雅",
    "courseContent": "以家庭为单位的健康照顾（2）",
    "classroom": "118大班"
  },
  {
    "color": "",
    "year": 2022,
    "month": 3,
    "day": 30,
    "begClass": 3,
    "endClass": 4,
    "courseName": "内科学",
    "teacher": "刘心强",
    "courseContent": "感染性心内膜炎",
    "classroom": "417大班"
  },
  {
    "color": "",
    "year": 2022,
    "month": 3,
    "day": 31,
    "begClass": 1,
    "endClass": 2,
    "courseName": "医学影像学",
    "teacher": "吴迪",
    "courseContent": "头颈部",
    "classroom": "217大班"
  },
  {
    "color": "",
    "year": 2022,
    "month": 3,
    "day": 31,
    "begClass": 3,
    "endClass": 4,
    "courseName": "内科学",
    "teacher": "蔡九妹",
    "courseContent": "心包疾病、心肌疾病",
    "classroom": "417大班"
  },
  {
    "color": "",
    "year": 2022,
    "month": 4,
    "day": 1,
    "begClass": 1,
    "endClass": 2,
    "courseName": "医学伦理学",
    "teacher": "李明",
    "courseContent": "临床常规诊治伦理",
    "classroom": "617大班"
  },
  {
    "color": "",
    "year": 2022,
    "month": 4,
    "day": 1,
    "begClass": 3,
    "endClass": 4,
    "courseName": "核医学",
    "teacher": "黄铀新",
    "courseContent": "心血管系统",
    "classroom": "118大班"
  },
  {
    "color": "",
    "year": 2022,
    "month": 4,
    "day": 1,
    "begClass": 5,
    "endClass": 6,
    "courseName": "中医学",
    "teacher": "孙小勇",
    "courseContent": "四诊",
    "classroom": "204大班"
  },
  {
    "color": "",
    "year": 2022,
    "month": 4,
    "day": 1,
    "begClass": 7,
    "endClass": 8,
    "courseName": "预防医学",
    "teacher": "邹琦",
    "courseContent": "第十章 烟草的控制",
    "classroom": "204大班"
  },
  {
    "color": "",
    "year": 2022,
    "month": 4,
    "day": 6,
    "begClass": 1,
    "endClass": 2,
    "courseName": "医学影像学",
    "teacher": "吴迪",
    "courseContent": "头颈部",
    "classroom": "118大班"
  },
  {
    "color": "",
    "year": 2022,
    "month": 4,
    "day": 6,
    "begClass": 3,
    "endClass": 4,
    "courseName": "内科学",
    "teacher": "王小萍",
    "courseContent": "心脏瓣膜病",
    "classroom": "517大班"
  },
  {
    "color": "",
    "year": 2022,
    "month": 4,
    "day": 7,
    "begClass": 5,
    "endClass": 6,
    "courseName": "核医学",
    "teacher": "黄铀新",
    "courseContent": "内分泌系统",
    "classroom": "202大班"
  },
  {
    "color": "",
    "year": 2022,
    "month": 4,
    "day": 7,
    "begClass": 7,
    "endClass": 8,
    "courseName": "内科学",
    "teacher": "王小萍",
    "courseContent": "心脏瓣膜病",
    "classroom": "302大班"
  },
  {
    "color": "",
    "year": 2022,
    "month": 4,
    "day": 8,
    "begClass": 1,
    "endClass": 2,
    "courseName": "全科医学概论",
    "teacher": "林芬",
    "courseContent": "以社区为范围的健康照顾",
    "classroom": "206大班"
  },
  {
    "color": "",
    "year": 2022,
    "month": 4,
    "day": 8,
    "begClass": 3,
    "endClass": 4,
    "courseName": "内科学",
    "teacher": "孟凡",
    "courseContent": "胃炎",
    "classroom": "206大班"
  },
  {
    "color": "",
    "year": 2022,
    "month": 4,
    "day": 8,
    "begClass": 5,
    "endClass": 6,
    "courseName": "中医学",
    "teacher": "孙小勇",
    "courseContent": "辨证",
    "classroom": "417大班"
  },
  {
    "color": "",
    "year": 2022,
    "month": 4,
    "day": 8,
    "begClass": 7,
    "endClass": 8,
    "courseName": "预防医学",
    "teacher": "熊亮(公卫)",
    "courseContent": "第十二章 身体活动促进",
    "classroom": "204大班"
  },
  {
    "color": "",
    "year": 2022,
    "month": 4,
    "day": 9,
    "begClass": 1,
    "endClass": 2,
    "courseName": "医学影像学",
    "teacher": "许红雨",
    "courseContent": "呼吸系统",
    "classroom": "217大班"
  },
  {
    "color": "",
    "year": 2022,
    "month": 4,
    "day": 9,
    "begClass": 3,
    "endClass": 4,
    "courseName": "预防医学",
    "teacher": "林芬",
    "courseContent": "第十三章 疾病的早期发现和处理",
    "classroom": "204大班"
  },
  {
    "color": "",
    "year": 2022,
    "month": 4,
    "day": 11,
    "begClass": 5,
    "endClass": 6,
    "courseName": "医学伦理学",
    "teacher": "李明",
    "courseContent": "讨论",
    "classroom": "思政实践基地3"
  },
  {
    "color": "",
    "year": 2022,
    "month": 4,
    "day": 11,
    "begClass": 7,
    "endClass": 8,
    "courseName": "中医学",
    "teacher": "孙小勇",
    "courseContent": "辨证",
    "classroom": "417大班"
  },
  {
    "color": "",
    "year": 2022,
    "month": 4,
    "day": 12,
    "begClass": 1,
    "endClass": 4,
    "courseName": "内科学",
    "teacher": "待定51",
    "courseContent": "心血管系统疾病",
    "classroom": "见习场所11（章）"
  },
  {
    "color": "",
    "year": 2022,
    "month": 4,
    "day": 12,
    "begClass": 5,
    "endClass": 6,
    "courseName": "医学影像学",
    "teacher": "许红雨",
    "courseContent": "呼吸系统",
    "classroom": "217大班"
  },
  {
    "color": "",
    "year": 2022,
    "month": 4,
    "day": 12,
    "begClass": 7,
    "endClass": 8,
    "courseName": "全科医学概论",
    "teacher": "刘艳红",
    "courseContent": "以预防为先导的健康照顾",
    "classroom": "206大班"
  },
  {
    "color": "",
    "year": 2022,
    "month": 4,
    "day": 13,
    "begClass": 3,
    "endClass": 4,
    "courseName": "内科学",
    "teacher": "范琳",
    "courseContent": "炎症性肠病",
    "classroom": "222大班"
  },
  {
    "color": "",
    "year": 2022,
    "month": 4,
    "day": 14,
    "begClass": 1,
    "endClass": 2,
    "courseName": "核医学",
    "teacher": "黄铀新",
    "courseContent": "泌尿系统",
    "classroom": "202大班"
  },
  {
    "color": "",
    "year": 2022,
    "month": 4,
    "day": 14,
    "begClass": 5,
    "endClass": 8,
    "courseName": "预防医学",
    "teacher": "古军旺;郝明;吴春眉;李思思;罗江洪;董明华;熊亮(公卫);何小娜",
    "courseContent": "实验二 诊断试验与筛检试验的评价",
    "classroom": "预防1-8实验室(黄金)"
  },
  {
    "color": "",
    "year": 2022,
    "month": 4,
    "day": 15,
    "begClass": 1,
    "endClass": 2,
    "courseName": "内科学",
    "teacher": "陈云",
    "courseContent": "消化性溃疡",
    "classroom": "417大班"
  },
  {
    "color": "",
    "year": 2022,
    "month": 4,
    "day": 15,
    "begClass": 3,
    "endClass": 4,
    "courseName": "医学影像学",
    "teacher": "邱兴庭",
    "courseContent": "循环系统",
    "classroom": "217大班"
  },
  {
    "color": "",
    "year": 2022,
    "month": 4,
    "day": 15,
    "begClass": 7,
    "endClass": 8,
    "courseName": "预防医学",
    "teacher": "邹丽君",
    "courseContent": "第十四章 传染病预防与控制（1）",
    "classroom": "204大班"
  },
  {
    "color": "",
    "year": 2022,
    "month": 4,
    "day": 17,
    "begClass": 1,
    "endClass": 4,
    "courseName": "全科医学概论",
    "teacher": "张琼;陈路军;朱韵雅;王宇",
    "courseContent": "以人为中心的照顾案例讨论",
    "classroom": "605讨论室"
  },
  {
    "color": "",
    "year": 2022,
    "month": 4,
    "day": 17,
    "begClass": 1,
    "endClass": 4,
    "courseName": "全科医学概论",
    "teacher": "张琼;陈路军;朱韵雅;王宇",
    "courseContent": "以人为中心的照顾案例讨论",
    "classroom": "607讨论室"
  },
  {
    "color": "",
    "year": 2022,
    "month": 4,
    "day": 18,
    "begClass": 1,
    "endClass": 2,
    "courseName": "中医学",
    "teacher": "刘振优",
    "courseContent": "防治原则",
    "classroom": "204大班"
  },
  {
    "color": "",
    "year": 2022,
    "month": 4,
    "day": 18,
    "begClass": 3,
    "endClass": 4,
    "courseName": "预防医学",
    "teacher": "邹丽君",
    "courseContent": "第十四章 传染病预防与控制（2）",
    "classroom": "204大班"
  },
  {
    "color": "",
    "year": 2022,
    "month": 4,
    "day": 18,
    "begClass": 5,
    "endClass": 6,
    "courseName": "医学影像学",
    "teacher": "邱兴庭",
    "courseContent": "循环系统",
    "classroom": "206大班"
  },
  {
    "color": "",
    "year": 2022,
    "month": 4,
    "day": 18,
    "begClass": 7,
    "endClass": 8,
    "courseName": "内科学",
    "teacher": "陈云",
    "courseContent": "消化性溃疡",
    "classroom": "219大班"
  },
  {
    "color": "",
    "year": 2022,
    "month": 4,
    "day": 19,
    "begClass": 3,
    "endClass": 4,
    "courseName": "内科学",
    "teacher": "周云",
    "courseContent": "急性胰腺炎",
    "classroom": "206大班"
  },
  {
    "color": "",
    "year": 2022,
    "month": 4,
    "day": 19,
    "begClass": 7,
    "endClass": 8,
    "courseName": "核医学",
    "teacher": "杨传盛(外聘)",
    "courseContent": "放射性核素治疗",
    "classroom": "623大班"
  },
  {
    "color": "",
    "year": 2022,
    "month": 4,
    "day": 20,
    "begClass": 1,
    "endClass": 2,
    "courseName": "医学伦理学",
    "teacher": "李明",
    "courseContent": "临床特殊科室、疾病和诊治伦理",
    "classroom": "318中班"
  },
  {
    "color": "",
    "year": 2022,
    "month": 4,
    "day": 20,
    "begClass": 3,
    "endClass": 4,
    "courseName": "核医学",
    "teacher": "杨传盛(外聘)",
    "courseContent": "放射性核素治疗",
    "classroom": "623大班"
  },
  {
    "color": "",
    "year": 2022,
    "month": 4,
    "day": 20,
    "begClass": 5,
    "endClass": 6,
    "courseName": "内科学",
    "teacher": "谢军",
    "courseContent": "肝硬化",
    "classroom": "222大班"
  },
  {
    "color": "",
    "year": 2022,
    "month": 4,
    "day": 21,
    "begClass": 3,
    "endClass": 4,
    "courseName": "内科学",
    "teacher": "谢军",
    "courseContent": "肝硬化",
    "classroom": "105大班"
  },
  {
    "color": "",
    "year": 2022,
    "month": 4,
    "day": 21,
    "begClass": 5,
    "endClass": 6,
    "courseName": "预防医学",
    "teacher": "刘艳红",
    "courseContent": "第十五章 慢性非传染性疾病预防与管理",
    "classroom": "204大班"
  },
  {
    "color": "",
    "year": 2022,
    "month": 4,
    "day": 22,
    "begClass": 1,
    "endClass": 2,
    "courseName": "预防医学",
    "teacher": "刘艳红",
    "courseContent": "第十六章 环境相关疾病及其预防控制",
    "classroom": "204大班"
  },
  {
    "color": "",
    "year": 2022,
    "month": 4,
    "day": 22,
    "begClass": 5,
    "endClass": 6,
    "courseName": "麻醉学",
    "teacher": "刘金龙",
    "courseContent": "第一章绪论第二章手术病人术前病情评估与准备",
    "classroom": "105大班"
  },
  {
    "color": "",
    "year": 2022,
    "month": 4,
    "day": 24,
    "begClass": 1,
    "endClass": 4,
    "courseName": "预防医学",
    "teacher": "熊亮(公卫);龚二生;何圣发;林芬;罗江洪;邹丽君;高艳芳;刘艳红",
    "courseContent": "实验三  糖尿病食谱编制",
    "classroom": "预防1-8实验室(黄金)"
  },
  {
    "color": "",
    "year": 2022,
    "month": 4,
    "day": 25,
    "begClass": 1,
    "endClass": 2,
    "courseName": "内科学",
    "teacher": "谢军",
    "courseContent": "肝性脑病",
    "classroom": "222大班"
  },
  {
    "color": "",
    "year": 2022,
    "month": 4,
    "day": 25,
    "begClass": 3,
    "endClass": 4,
    "courseName": "医学伦理学",
    "teacher": "王志坚",
    "courseContent": "医疗人际关系伦理",
    "classroom": "217大班"
  },
  {
    "color": "",
    "year": 2022,
    "month": 4,
    "day": 25,
    "begClass": 7,
    "endClass": 8,
    "courseName": "中医学",
    "teacher": "钟斌A",
    "courseContent": "中药",
    "classroom": "417大班"
  },
  {
    "color": "",
    "year": 2022,
    "month": 4,
    "day": 26,
    "begClass": 1,
    "endClass": 2,
    "courseName": "医学影像学",
    "teacher": "曹洁莹",
    "courseContent": "乳腺",
    "classroom": "304大班"
  }
]